example/__init__.py
example/example1.py
market_financialexpress/FinancialExpress_Stock.py
market_financialexpress/__init__.py
market_financialexpress/__main__.py
market_financialexpress/example/__init__.py
market_financialexpress/example/example1.py
market_financialexpress-1.0.0.dist-info/LICENSE
market_financialexpress-1.0.0.dist-info/METADATA
market_financialexpress-1.0.0.dist-info/WHEEL
market_financialexpress-1.0.0.dist-info/entry_points.txt
market_financialexpress-1.0.0.dist-info/top_level.txt
market_financialexpress-1.0.0.dist-info/RECORD
